frozenmap/__init__.py
frozenmap/_frozendict.cpython-35m-darwin.so
frozenmap/frozendict.cpython-35m-darwin.so
frozenmap/frozendict.py
frozenmap/frozenmap.cpython-35m-darwin.so
frozenmap/frozenmap.py
frozenmap/test/__init__.py
frozenmap/test/test_frozendict.py
frozenmap-0.6.dist-info/LICENSE.txt
frozenmap-0.6.dist-info/METADATA
frozenmap-0.6.dist-info/WHEEL
frozenmap-0.6.dist-info/top_level.txt
frozenmap-0.6.dist-info/RECORD
